rocket/__init__.py
rocket/rocket.py
rocketnoussa/__init__.py
rocketnoussa/rocket.py
rocketnoussa-1.0.0.dist-info/LICENSE.txt
rocketnoussa-1.0.0.dist-info/METADATA
rocketnoussa-1.0.0.dist-info/WHEEL
rocketnoussa-1.0.0.dist-info/top_level.txt
rocketnoussa-1.0.0.dist-info/RECORD
