Metadata-Version: 2.1
Name: rocketnoussa
Version: 1.0.0
Summary: An awesome package that does something
Home-page: http://pypi.python.org/pypi/rocketnoussa/
Author: Noussaiba Belhouari
Author-email: n.belhouari@esi-sba.dz
License: LICENSE.txt
License-File: LICENSE.txt
